compilere/__init__.py
compilere/__main__.py
python_compilere-0.0.1.dist-info/METADATA
python_compilere-0.0.1.dist-info/WHEEL
python_compilere-0.0.1.dist-info/top_level.txt
python_compilere-0.0.1.dist-info/RECORD
