Metadata-Version: 2.1
Name: python-compilere
Version: 0.0.1
Summary: the compiler make in python
Home-page: UNKNOWN
Author: umar moiz qurashi
Author-email: umar.maq@yandex.com
License: ""
Platform: UNKNOWN
